smallPowerDash/fitSmallPowerData.py
smallPowerDash/indicateurs
smallPowerDash/smallPower.py
smallPowerDash/smallPowerTabs.py
smallPowerDash/confFiles/ALPHA - BD Instrum XL_V2.47.xlsm
smallPowerDash/confFiles/dashboards.conf
smallPowerDash/confFiles/devices_HUB_v1.ods
smallPowerDash/confFiles/formulaIndicators.md
smallPowerDash/confFiles/logVersionSmallPower.md
smallPowerDash/confFiles/my_cert.pem
smallPowerDash/confFiles/my_private_key.pem
smallPowerDash/confFiles/palettes.pkl
smallPowerDash/confFiles/plc_smallpower.pkl
smallPowerDash/confFiles/smallpower_conffiles.pkl
smallPowerDash/confFiles/smallpower_configfiles.ods
smallPowerDash/confFiles/spark.conf
smallPowerDash/confFiles/pictures/angrypainter.gif
smallPowerDash/confFiles/pictures/logo_sylfen.png
smallPowerDash/confFiles/pictures/peintrepalette.jpeg
smallPowerDash-4.3.2.dist-info/METADATA
smallPowerDash-4.3.2.dist-info/WHEEL
smallPowerDash-4.3.2.dist-info/top_level.txt
smallPowerDash-4.3.2.dist-info/RECORD
